{
 "id": "galatians",
 "hebrew": "GALATIANS",
 "english": "Galatians",
 "section": "Messianic",
 "chapter_count": 6,
 "chapters": {
  "1": {
   "verses": [
    {
     "n": 1,
     "t": "Sha’ul, an emissary – not from men, nor by a man, but by <span class=\"dn\">Yahusha</span> <span class=\"dn\">Mashiach</span> and <span class=\"dn\">Aluahim</span> the Father who raised Him from the dead –"
    },
    {
     "n": 2,
     "t": "and all the brothers who are with me, to the qahalim of Galatia:"
    },
    {
     "n": 3,
     "t": "Chen to you and shalom from <span class=\"dn\">Aluahim</span> the Father and our Master <span class=\"dn\">Yahusha</span> <span class=\"dn\">Mashiach</span>,"
    },
    {
     "n": 4,
     "t": "who gave Himself for our sins, to deliver us out of this present wicked age, according to the desire of our <span class=\"dn\">Aluahim</span> and Father,"
    },
    {
     "n": 5,
     "t": "to whom be the praise forever and ever. Amĕn."
    },
    {
     "n": 6,
     "t": "I marvel that you are so readily turning away from Him who called you in the chen of <span class=\"dn\">Mashiach</span>, to a different ‘Besorah,’"
    },
    {
     "n": 7,
     "t": "which is not another, only there are some who are troubling you and wishing to pervert the Besorah of <span class=\"dn\">Mashiach</span>."
    },
    {
     "n": 8,
     "t": "However, even if we, or a mal'ak out of shamayim, bring a ‘Besorah’ to you beside what we announced to you, let him be accursed."
    },
    {
     "n": 9,
     "t": "As we have said before and now I say again, if anyone brings a ‘Besorah’ to you beside what you have received, let him be accursed."
    },
    {
     "n": 10,
     "t": "For do I now persuade men, or <span class=\"dn\">Aluahim</span>? Or do I seek to please men? For if I still pleased men, I should not be a servant of <span class=\"dn\">Mashiach</span>."
    },
    {
     "n": 11,
     "t": "And I make known to you, brothers, that the Besorah announced by me is not according to man."
    },
    {
     "n": 12,
     "t": "For I did not receive it from man, nor was I taught it, but through a revelation of <span class=\"dn\">Yahusha</span> <span class=\"dn\">Mashiach</span>."
    },
    {
     "n": 13,
     "t": "For you have heard of my former way of life in Yahhuḏaism, how intensely I persecuted the qahal of <span class=\"dn\">Aluahim</span> and ravaged it."
    },
    {
     "n": 14,
     "t": "And I progressed in Yahuḏaism beyond many of my age in my race, being more exceedingly ardent for the traditions of my fathers."
    },
    {
     "n": 15,
     "t": "But when it pleased <span class=\"dn\">Aluahim</span>, who separated me from my mother’s womb and called me by His chen,"
    },
    {
     "n": 16,
     "t": "to reveal His Son in me, that I might bring Him, the Besorah, to the gentiles, I did not immediately consult with flesh and blood,"
    },
    {
     "n": 17,
     "t": "neither did I go up to Yahrushalayim, to those who were emissaries before me. But I went to Araḇia and returned again to Damascus."
    },
    {
     "n": 18,
     "t": "Then after three years I went up to Yahrushalayim to learn from Kĕpha and remained with him for fifteen days."
    },
    {
     "n": 19,
     "t": "And I saw no other of the emissaries except Ya‛aqoḇ, the brother of the Master."
    },
    {
     "n": 20,
     "t": "And what I write to you, see, before <span class=\"dn\">Aluahim</span>, I do not lie."
    },
    {
     "n": 21,
     "t": "Then I went into the districts of Syria and of Kilikia."
    },
    {
     "n": 22,
     "t": "And I was still not known by sight to the qahalim of Yahuḏah which were in <span class=\"dn\">Mashiach</span>,"
    },
    {
     "n": 23,
     "t": "but they were hearing only that, “The one who once persecuted us now brings as Besorah the belief which he once ravaged.”"
    },
    {
     "n": 24,
     "t": "So they were esteeming <span class=\"dn\">Aluahim</span> in me."
    }
   ],
   "page": 534,
   "pdf": "TheBesorah-all.0002.pdf"
  },
  "2": {
   "verses": [
    {
     "n": 1,
     "t": "Then after fourteen years I again went up to Yahrushalayim, with Barnaḇah, taking Titus along too."
    },
    {
     "n": 2,
     "t": "And I went up by revelation and laid before them that Besorah which I proclaim among the gentiles, but separately to those who were esteemed, lest somehow I run, or had run, in vain."
    },
    {
     "n": 3,
     "t": "But not even Titus who was with me, though a Greek, was compelled to be circumcised."
    },
    {
     "n": 4,
     "t": "But as for the false brothers, sneakingly brought in, who sneaked in to spy out our freedom which we have in <span class=\"dn\">Mashiach</span> <span class=\"dn\">Yahusha</span> in order to enslave us,"
    },
    {
     "n": 5,
     "t": "to these we did not yield in subjection, not even for an hour, so that the truth of the Besorah remains with you."
    },
    {
     "n": 6,
     "t": "But from those who were esteemed to be whatever – what they were, it makes no difference to me, <span class=\"dn\">Aluahim</span> shows no partiality – for those who were esteemed contributed naught to me."
    },
    {
     "n": 7,
     "t": "But on the contrary, when they saw that the Besorah to the uncircumcised had been entrusted to me, even as Kĕpha to the circumcised –"
    },
    {
     "n": 8,
     "t": "for He who worked in Kĕpha to make him an emissary to the circumcised also worked in me for the gentiles."
    },
    {
     "n": 9,
     "t": "So when Ya‛aqoḇ, Kĕpha and Yahuchanon, who seemed to be supports, came to know the chen that had been given to me, they gave me and Barnaḇah the right hand of fellowship, in order that we go to the gentiles and they to the circumcised,"
    },
    {
     "n": 10,
     "t": "only that we might remember the poor, which I myself was eager to do."
    },
    {
     "n": 11,
     "t": "And when Kĕpha had come to Antioch, I withstood him to his face, because he was at fault."
    },
    {
     "n": 12,
     "t": "For before some came from Ya‛aqoḇ, he was eating with the gentiles, but when they came, he began to withdraw and separate himself, in fear of those of the circumcision."
    },
    {
     "n": 13,
     "t": "And the rest of the Yahuḏim joined him in hypocrisy, so that even Barnaḇah was led away by their hypocrisy."
    },
    {
     "n": 14,
     "t": "But when I saw that they are not walking straight according to the truth of the Besorah, I said to Kĕpha before them all, “If you, being a Yahhuḏite, live as a gentile and not as the Yahuḏim, why do you compel gentiles to live as Yahuḏim?"
    },
    {
     "n": 15,
     "t": "“We, Yahuḏim by nature and not of the gentiles, sinners,"
    },
    {
     "n": 16,
     "t": "knowing that a man is not declared right by works of Torah, but through belief in <span class=\"dn\">Yahusha</span> <span class=\"dn\">Mashiach</span>, even we have believed in <span class=\"dn\">Mashiach</span> <span class=\"dn\">Yahusha</span>, in order to be declared right by belief in <span class=\"dn\">Mashiach</span> and not by works of Torah, because by works of Torah no flesh shall be declared right."
    },
    {
     "n": 17,
     "t": "“And if, while seeking to be declared right by <span class=\"dn\">Mashiach</span>, we ourselves also are found sinners, is <span class=\"dn\">Mashiach</span> then a servant of sin? Let it not be!"
    },
    {
     "n": 18,
     "t": "“For if I rebuild what I once overthrew, I establish myself a transgressor."
    },
    {
     "n": 19,
     "t": "“For through Torah I died to Torah, in order to live to <span class=\"dn\">Aluahim</span>."
    },
    {
     "n": 20,
     "t": "“I have been impaled with <span class=\"dn\">Mashiach</span> and I no longer live, but <span class=\"dn\">Mashiach</span> lives in me. And that which I now live in the flesh I live by belief in the Son of <span class=\"dn\">Aluahim</span>, who loved me and gave Himself for me."
    },
    {
     "n": 21,
     "t": "“I do not set aside the chen of <span class=\"dn\">Aluahim</span>, for if righteousness is through Torah, then <span class=\"dn\">Mashiach</span> died for naught.”"
    }
   ],
   "page": 534,
   "pdf": "TheBesorah-all.0002.pdf"
  },
  "3": {
   "verses": [
    {
     "n": 1,
     "t": "O senseless Galatians! Who has put you under a spell, not to obey the truth – before whose eyes <span class=\"dn\">Yahusha</span> <span class=\"dn\">Mashiach</span> was clearly portrayed among you as impaled?"
    },
    {
     "n": 2,
     "t": "This only I wish to learn from you: Did you receive the Ruach by works of Torah, or by the hearing of belief?"
    },
    {
     "n": 3,
     "t": "Are you so senseless? Having begun in the Ruach, do you now end in the flesh?"
    },
    {
     "n": 4,
     "t": "Have you suffered so much in vain – if indeed in vain?"
    },
    {
     "n": 5,
     "t": "Is He, then, who is supplying the Ruach to you and working miracles among you, doing it by works of Torah, or by hearing of belief?"
    },
    {
     "n": 6,
     "t": "Even so Aḇrahim “did believe <span class=\"dn\">Aluahim</span> and it was reckoned unto him as righteousness.”"
    },
    {
     "n": 7,
     "t": "Know, then, that those who are of belief are sons of Aḇrahim."
    },
    {
     "n": 8,
     "t": "And the Scripture, having foreseen that <span class=\"dn\">Aluahim</span> would declare right the nations by belief, announced the Besorah to Aḇrahim beforehand, saying, “All the nations shall be baruk in you,”"
    },
    {
     "n": 9,
     "t": "so that those who are of belief are baruk with Aḇrahim, the believer."
    },
    {
     "n": 10,
     "t": "For as many as are of works of Torah are under the curse, for it has been written, “Cursed is everyone who does not continue in all that has been written in the book of the Torah, to do them.”"
    },
    {
     "n": 11,
     "t": "And that no one is declared right by Torah before <span class=\"dn\">Aluahim</span> is clear, for “The righteous shall live by belief.”"
    },
    {
     "n": 12,
     "t": "And the Torah is not of belief, but “The man who does them shall live by them.”"
    },
    {
     "n": 13,
     "t": "<span class=\"dn\">Mashiach</span> redeemed us from the curse of the Torah, having become a curse for us – for it has been written, “Cursed is everyone who hangs upon a tree. ” –"
    },
    {
     "n": 14,
     "t": "in order that the berakah of Aḇrahim might come upon the nations in <span class=\"dn\">Mashiach</span> <span class=\"dn\">Yahusha</span>, to receive the promise of the Ruach through belief."
    },
    {
     "n": 15,
     "t": "Brothers, as a man I say it: a berith, even though it is man’s, yet if it is confirmed, no one sets it aside, or adds to it."
    },
    {
     "n": 16,
     "t": "But the promises were spoken to Aḇrahim and to his Seed. He does not say, “And to seeds,” as of many, but as of one, “And to your Seed,” who is <span class=\"dn\">Mashiach</span>."
    },
    {
     "n": 17,
     "t": "Now this I say, Torah, that came four hundred and thirty years later, does not annul a berith previously confirmed by <span class=\"dn\">Aluahim</span> in <span class=\"dn\">Mashiach</span>, so as to do away with the promise."
    },
    {
     "n": 18,
     "t": "For if the inheritance is by Torah, it is no longer by promise, but <span class=\"dn\">Aluahim</span> gave it to Aḇrahim through a promise."
    },
    {
     "n": 19,
     "t": "Why, then, the Torah? It was added because of transgressions, until the Seed should come to whom the promise was made. And it was ordained through mal'akim in the hand of a mediator."
    },
    {
     "n": 20,
     "t": "The Mediator, however, is not of one, but <span class=\"dn\">Aluahim</span> is one."
    },
    {
     "n": 21,
     "t": "Is the Torah then against the promises of <span class=\"dn\">Aluahim</span>? Let it not be! For if a law had been given that was able to make alive, truly righteousness would have been by Torah."
    },
    {
     "n": 22,
     "t": "But the Scripture has shut up all mankind under sin, that the promise by belief in <span class=\"dn\">Yahusha</span> <span class=\"dn\">Mashiach</span> might be given to those who believe."
    },
    {
     "n": 23,
     "t": "But before belief came, we were being guarded under Torah, having been shut up for the belief being about to be revealed."
    },
    {
     "n": 24,
     "t": "Therefore the Torah became our trainer unto <span class=\"dn\">Mashiach</span>, in order to be declared right by belief."
    },
    {
     "n": 25,
     "t": "And after belief has come, we are no longer under a trainer."
    },
    {
     "n": 26,
     "t": "For you are all sons of <span class=\"dn\">Aluahim</span> through belief in <span class=\"dn\">Mashiach</span> <span class=\"dn\">Yahusha</span>."
    },
    {
     "n": 27,
     "t": "For as many of you as were immersed into <span class=\"dn\">Mashiach</span> have put on <span class=\"dn\">Mashiach</span>."
    },
    {
     "n": 28,
     "t": "There is not Yahudi nor Greek, there is not slave nor free, there is not male and female, for you are all one in <span class=\"dn\">Mashiach</span> <span class=\"dn\">Yahusha</span>."
    },
    {
     "n": 29,
     "t": "And if you are of <span class=\"dn\">Mashiach</span>, then you are seed of Aḇrahim and heirs according to promise."
    }
   ],
   "page": 535,
   "pdf": "TheBesorah-all.0002.pdf"
  },
  "4": {
   "verses": [
    {
     "n": 1,
     "t": "And I say, for as long as the heir is a child, he is no different from a slave, though he is master of all,"
    },
    {
     "n": 2,
     "t": "but is under guardians and trustees til the time prearranged by the father."
    },
    {
     "n": 3,
     "t": "So we also, when we were children, were under the elementary matters of the world, being enslaved."
    },
    {
     "n": 4,
     "t": "But when the completion of the time came, <span class=\"dn\">Aluahim</span> sent forth His Son, born of a woman, born under Torah,"
    },
    {
     "n": 5,
     "t": "to redeem those who were under Torah, in order to receive the adoption as sons."
    },
    {
     "n": 6,
     "t": "And because you are sons, <span class=\"dn\">Aluahim</span> has sent forth the Ruach of His Son into your hearts, crying, “Abba, Father!”"
    },
    {
     "n": 7,
     "t": "So you are no longer a slave but a son and if a son, also an heir of <span class=\"dn\">Aluahim</span> through <span class=\"dn\">Mashiach</span>."
    },
    {
     "n": 8,
     "t": "But then, indeed, not knowing <span class=\"dn\">Aluahim</span>, you served those which by nature are not mighty ones."
    },
    {
     "n": 9,
     "t": "But now after you have known <span class=\"dn\">Aluahim</span>, or rather are known by <span class=\"dn\">Aluahim</span>, how do you turn again to the weak and poor elementary matters, to which you wish to be enslaved again?"
    },
    {
     "n": 10,
     "t": "You observe days and months and sea sons and years."
    },
    {
     "n": 11,
     "t": "I fear for you, lest by any means I have laboured for you in vain."
    },
    {
     "n": 12,
     "t": "Brothers, I beg you to become as I am, because I am as you are. You did not wrong me at all."
    },
    {
     "n": 13,
     "t": "But you know that through weakness of the flesh I brought the Besorah to you before."
    },
    {
     "n": 14,
     "t": "And my trial which was in my flesh you did not despise or reject, but you received me as a mal'ak of <span class=\"dn\">Aluahim</span>, as <span class=\"dn\">Mashiach</span> <span class=\"dn\">Yahusha</span>."
    },
    {
     "n": 15,
     "t": "What then was your blessedness? For I bear you witness, that if possible, you would have plucked out your own eyes and given them to me."
    },
    {
     "n": 16,
     "t": "So then, have I become your enemy, speaking truth to you?"
    },
    {
     "n": 17,
     "t": "They are ardent towards you, for no good, but they wish to shut you out, that you might be ardent towards them."
    },
    {
     "n": 18,
     "t": "And it is good always to be ardent in what is good and not only when I am present with you."
    },
    {
     "n": 19,
     "t": "My little children, for whom I am again in birth pains until <span class=\"dn\">Mashiach</span> is formed in you,"
    },
    {
     "n": 20,
     "t": "even now I wish to be present with you now and to change my voice, for I have doubts about you."
    },
    {
     "n": 21,
     "t": "Say to me, you who wish to be under Torah, do you not hear the Torah?"
    },
    {
     "n": 22,
     "t": "For it has been written that Aḇrahim had two sons, one by a female servant, the other by a free woman."
    },
    {
     "n": 23,
     "t": "But he who was of the female servant was born according to the flesh and he of the free woman through promise."
    },
    {
     "n": 24,
     "t": "This is allegorical, for these are the two berithot: one indeed from Mount Sinai which brings forth slavery, which is Haḡar,"
    },
    {
     "n": 25,
     "t": "for this Haḡar is Mount Sinai in Araḇia and corresponds to Yahrushalayim which now is and is in slavery with her children."
    },
    {
     "n": 26,
     "t": "But the Yahrushalayim above is free, which is the mother of us all."
    },
    {
     "n": 27,
     "t": "For it has been written, “Rejoice, O barren, you who do not bear! Break forth and shout, you who do not have birth pains! For the deserted one has many more children than she who has a husband.”"
    },
    {
     "n": 28,
     "t": "And we, brothers, as Yahtsḥaq was, are children of promise."
    },
    {
     "n": 29,
     "t": "But, as he who was born according to the flesh then persecuted him born according to the Ruach, so also now."
    },
    {
     "n": 30,
     "t": "But what does the Scripture say? “Cast out the female servant and her son, for the son of the female servant shall by no means be heir with the son of the free woman.”"
    },
    {
     "n": 31,
     "t": "Therefore, brothers, we are not children of the female servant but of the free woman."
    }
   ],
   "page": 536,
   "pdf": "TheBesorah-all.0002.pdf"
  },
  "5": {
   "verses": [
    {
     "n": 1,
     "t": "In the freedom with which <span class=\"dn\">Mashiach</span> has made us free, stand firm, then and do not again be held with a yoke of slavery."
    },
    {
     "n": 2,
     "t": "See, I, Sha’ul, say to you that if you become circumcised, <span class=\"dn\">Mashiach</span> shall be of no use to you."
    },
    {
     "n": 3,
     "t": "And I witness again to every man being circumcised that he is a debtor to do the entire Torah."
    },
    {
     "n": 4,
     "t": "You who are declared right by Torah have severed yourselves from <span class=\"dn\">Mashiach</span>, you have fallen from chen."
    },
    {
     "n": 5,
     "t": "For we, in Ruach, by belief, eagerly wait for the expectation of righteousness."
    },
    {
     "n": 6,
     "t": "For in <span class=\"dn\">Mashiach</span> <span class=\"dn\">Yahusha</span> neither circumcision nor uncircumcision has any strength, but belief working through love."
    },
    {
     "n": 7,
     "t": "You were running well, who held you back from obeying the truth?"
    },
    {
     "n": 8,
     "t": "That persuasion does not come from Him who calls you."
    },
    {
     "n": 9,
     "t": "A little leaven leavens all the lump."
    },
    {
     "n": 10,
     "t": "I trust in you, in the Master, that you shall have no other mind. And he who is troubling you shall bear his mishpat, whoever he is."
    },
    {
     "n": 11,
     "t": "And I, brothers, if I still proclaim circumcision, why am I still persecuted? Then the stumbling-block of the stake has been set aside."
    },
    {
     "n": 12,
     "t": "O that those who disturb you would even cut themselves off!"
    },
    {
     "n": 13,
     "t": "For you, brothers, have been called to freedom, only do not use freedom as an occasion for the flesh, but through love serve one another."
    },
    {
     "n": 14,
     "t": "For the entire Torah is completed in one word, in this, “You shall love your neighbour as yourself.”"
    },
    {
     "n": 15,
     "t": "And if you bite and devour one another, beware lest you be consumed by one another!"
    },
    {
     "n": 16,
     "t": "And I say: walk in the Ruach and you shall not accomplish the lust of the flesh."
    },
    {
     "n": 17,
     "t": "For the flesh lusts against the Ruach and the Ruach against the flesh. And these are opposed to each other, so that you do not do what you desire to do."
    },
    {
     "n": 18,
     "t": "But if you are led by the Ruach, you are not under Torah."
    },
    {
     "n": 19,
     "t": "And the works of the flesh are wellknown, which are these: adultery, whoring, uncleanness, indecency,"
    },
    {
     "n": 20,
     "t": "idolatry, drug sorcery, hatred, quarrels, jealousies, fits of rage, selfish ambitions, dissensions, factions,"
    },
    {
     "n": 21,
     "t": "envy, murders, drunkenness, wild parties and the like – of which I forewarn you, even as I also said before, that those who practise such as these shall not inherit the reign of <span class=\"dn\">Aluahim</span>."
    },
    {
     "n": 22,
     "t": "But the fruit of the Ruach is love, joy, shalom, patience, kindness, goodness, trustworthiness,"
    },
    {
     "n": 23,
     "t": "gentleness, self-control. Against such there is no Torah."
    },
    {
     "n": 24,
     "t": "And those who are of <span class=\"dn\">Mashiach</span> have impaled the flesh with its passions and the desires."
    },
    {
     "n": 25,
     "t": "If we live in the Ruach, let us also walk in the Ruach."
    },
    {
     "n": 26,
     "t": "Let us not become conceited, provoking one another, envying one another."
    }
   ],
   "page": 537,
   "pdf": "TheBesorah-all.0002.pdf"
  },
  "6": {
   "verses": [
    {
     "n": 1,
     "t": "Brothers, if a man is overtaken in some trespass, you the spiritual ones, set such a one straight in a ruach of meekness, looking at yourself lest you be tried too."
    },
    {
     "n": 2,
     "t": "Bear one another’s burdens and so complete the Torah of <span class=\"dn\">Mashiach</span>."
    },
    {
     "n": 3,
     "t": "For if anyone thinks himself to be somebody, when he is not, he deceives himself."
    },
    {
     "n": 4,
     "t": "But let each one examine his own work and then he shall have boasting in himself alone and not in another."
    },
    {
     "n": 5,
     "t": "For each one shall bear his own burden."
    },
    {
     "n": 6,
     "t": "And let him who is instructed in the Word share in all that is good, with him who is instructing."
    },
    {
     "n": 7,
     "t": "Do not be led astray: <span class=\"dn\">Aluahim</span> is not mocked, for whatever a man sows, that he shall also reap."
    },
    {
     "n": 8,
     "t": "Because he who sows to his own flesh shall reap corruption from the flesh, but he who sows to the Ruach shall reap everlasting life from the Ruach."
    },
    {
     "n": 9,
     "t": "And let us not lose heart in doing good, for in due season we shall reap if we do not grow weary."
    },
    {
     "n": 10,
     "t": "So then, as we have occasion, let us do good to all, especially to those who are of the household of the belief."
    },
    {
     "n": 11,
     "t": "See with what big letters I have written to you with my own hand!"
    },
    {
     "n": 12,
     "t": "As many as wish to make a good show in the flesh, these compel you to be circumcised, only so that they should not be persecuted for the stake of <span class=\"dn\">Mashiach</span>."
    },
    {
     "n": 13,
     "t": "For those who are circumcised do not even watch over the Torah, but they wish to have you circumcised so that they might boast in your flesh."
    },
    {
     "n": 14,
     "t": "And for me, let it not be that I should boast except in the stake of our Master <span class=\"dn\">Yahusha</span> <span class=\"dn\">Mashiach</span>, through whom the world has been impaled to me and I to the world."
    },
    {
     "n": 15,
     "t": "For in <span class=\"dn\">Mashiach</span> <span class=\"dn\">Yahusha</span> neither circumcision nor uncircumcision has any strength, but a renewed creature."
    },
    {
     "n": 16,
     "t": "And as many as walk according to this rule, shalom and compassion be upon them and upon the <span class=\"dn\">Yasharal</span> of <span class=\"dn\">Aluahim</span>."
    },
    {
     "n": 17,
     "t": "From now on let no one trouble me, for I bear in my body the scars of the Master <span class=\"dn\">Yahusha</span>."
    },
    {
     "n": 18,
     "t": "The chen of our Master <span class=\"dn\">Yahusha</span> <span class=\"dn\">Mashiach</span> be with your ruach, brothers. Amĕn."
    }
   ],
   "page": 538,
   "pdf": "TheBesorah-all.0002.pdf"
  }
 }
}